LICENSE
aio_recurring/__init__.py
aio_recurring/job.py
aio_recurring-0.1.2.dist-info/LICENSE
aio_recurring-0.1.2.dist-info/WHEEL
aio_recurring-0.1.2.dist-info/METADATA
aio_recurring-0.1.2.dist-info/RECORD
