Metadata-Version: 2.1
Name: aio-recurring
Version: 0.1.2
Summary: Schedule recurring coroutines using asyncio
Home-page: https://github.com/skonik/aio-recurring
License: MIT
Keywords: asyncio
Author: Sergey Konik
Author-email: s.konik.job@gmail.com
Requires-Python: >=3.7,<4.0
Classifier: License :: OSI Approved :: MIT License
Classifier: Programming Language :: Python :: 3
Classifier: Programming Language :: Python :: 3.7
Classifier: Programming Language :: Python :: 3.8
Classifier: Programming Language :: Python :: 3.9
Project-URL: Repository, https://github.com/skonik/aio-recurring
